glyphcore/__init__.py
glyphcore/cli.py
glyphcore/compliance/__init__.py
glyphcore/compliance/statusblock.py
glyphcore/core/__init__.py
glyphcore/core/signal.py
glyphcore/engine/__init__.py
glyphcore/engine/analyzer.py
glyphcore/engine/engine.py
glyphcore/engine/normalize.py
glyphcore/renderers/__init__.py
glyphcore/renderers/gui.py
glyphcore/renderers/signal_block.py
glyphcore/renderers/tui.py
glyphcore-0.3.0.dist-info/licenses/LICENSE
glyphcore-0.3.0.dist-info/METADATA
glyphcore-0.3.0.dist-info/WHEEL
glyphcore-0.3.0.dist-info/entry_points.txt
glyphcore-0.3.0.dist-info/top_level.txt
glyphcore-0.3.0.dist-info/RECORD
