Metadata-Version: 2.4
Name: glyphcore
Version: 0.3.0
Summary: Terminal-native semantic status framework for system state summarization
Author-email: Tanishq Dasari <tanishqdasari2004@gmail.com>
License: MIT License
Keywords: tui,observability,status,signals,monitoring,terminal,domain-agnostic
Classifier: Programming Language :: Python :: 3
Classifier: License :: OSI Approved :: MIT License
Classifier: Operating System :: OS Independent
Classifier: Intended Audience :: Developers
Classifier: Topic :: System :: Monitoring
Classifier: Topic :: Software Development :: Libraries
Requires-Python: >=3.10
License-File: LICENSE
Provides-Extra: gui
Requires-Dist: plotly>=5.0; extra == "gui"
Requires-Dist: matplotlib>=3.7; extra == "gui"
Provides-Extra: data
Requires-Dist: pandas>=2.0; extra == "data"
Provides-Extra: tui
Requires-Dist: textual>=0.40; extra == "tui"
Provides-Extra: dev
Requires-Dist: pytest; extra == "dev"
Requires-Dist: black; extra == "dev"
Requires-Dist: ruff; extra == "dev"
Requires-Dist: mypy; extra == "dev"
Dynamic: license-file
